{"eventId": "2884", "documentCode": "TTEMSINGLES-----------QFNL000100----------", "subEventName": "Men's Singles", "subEventDescription": "Men's Singles - Quarterfinal - Match 1", "matchConfig": {"bestOfXGames": 5, "maxPointsPerGame": 11, "advantagePerGame": 2, "suddenDeathPoint": 99, "maxChallengesPerCompetitor": 99, "yellowCard": true, "yellowRed1": true, "yellowRed2": true, "tTRReview": false}, "venueName": "OMEGA Sport Center", "tableNumber": "T01", "tableName": "Table 1", "competitiors": [{"competitorType": "H", "competitiorId": "135888", "competitiorName": "XIANG Peng", "competitiorOrg": "CHN", "compCardY": "0", "compCardYR1": "0", "compCardYR2": "0", "compTimeout": "0", "compMedicalTimeout": "", "players": [{"playerId": "135888", "playerName": "XIANG Peng", "playerGivenName": null, "playerFamilyName": null, "playerOrgCode": "CHN", "playerPosition": 1}], "scores": "11,11,11,0,0", "irm": null}, {"competitorType": "A", "competitiorId": "104036", "competitiorName": "JANCARIK Lubomir", "competitiorOrg": "CZE", "compCardY": "0", "compCardYR1": "0", "compCardYR2": "0", "compTimeout": "1", "compMedicalTimeout": "", "players": [{"playerId": "104036", "playerName": "JANCARIK Lubomir", "playerGivenName": null, "playerFamilyName": null, "playerOrgCode": "CZE", "playerPosition": 2}], "scores": "3,5,6,0,0", "irm": null}], "currentGameNumber": 3, "full_msg": null, "gameScores": "11-3,11-5,11-6,0-0,0-0", "resultsGameScores": "11-3,11-5,11-6,0-0,0-0", "overallScores": "3-0", "resultOverallScores": "3-0", "resultStatus": "OFFICIAL", "action": {"actionType": "OF", "serverPlayer": "104036", "serverReceiver": "135888", "serverNext": "104036", "serverCompetitor": "104036", "receiverNext": "135888"}, "resultSet": null, "matchDateTime": {"duration": "00:22:00", "startDateLocal": "08/24/2024 13:45:00", "startDateUTC": "08/24/2024 11:45:00"}, "teamParentData": null, "playByPlaySequenceNumber": "137", "teamMatchNo": "0", "teamMatchScores": "0-0,0-0,0-0,0-0,0-0", "teamMatchScoresSummary": "0", "matchStartTimeUTC": null}