{"eventId": "2886", "documentCode": "TTEMSINGLES-----------8FNL000100----------", "subEventName": "Men's Singles", "subEventDescription": "Men's Singles - Round of 16 - Match 1", "matchConfig": {"bestOfXGames": 5, "maxPointsPerGame": 11, "advantagePerGame": 2, "suddenDeathPoint": 99, "maxChallengesPerCompetitor": 99, "yellowCard": true, "yellowRed1": true, "yellowRed2": true, "tTRReview": false}, "venueName": "Halmstad Arena", "tableNumber": "T01", "tableName": "Table 1", "competitiors": [{"competitorType": "H", "competitiorId": "116846", "competitiorName": "ERIKSSON Anders", "competitiorOrg": "SWE", "compCardY": "0", "compCardYR1": "0", "compCardYR2": "0", "compTimeout": "1", "compMedicalTimeout": "", "players": [{"playerId": "116846", "playerName": "ERIKSSON Anders", "playerGivenName": null, "playerFamilyName": null, "playerOrgCode": "SWE", "playerPosition": 1}], "scores": "8,5,9,0,0", "irm": null}, {"competitorType": "A", "competitiorId": "145799", "competitiorName": "BERTELSMEIER Andre", "competitiorOrg": "GER", "compCardY": "0", "compCardYR1": "0", "compCardYR2": "0", "compTimeout": "0", "compMedicalTimeout": "", "players": [{"playerId": "145799", "playerName": "BERTELSMEIER Andre", "playerGivenName": null, "playerFamilyName": null, "playerOrgCode": "GER", "playerPosition": 2}], "scores": "11,11,11,0,0", "irm": null}], "currentGameNumber": 3, "full_msg": null, "gameScores": "8-11,5-11,9-11,0-0,0-0", "resultsGameScores": "8-11,5-11,9-11,0-0,0-0", "overallScores": "0-3", "resultOverallScores": "0-3", "resultStatus": "OFFICIAL", "action": {"actionType": "OF", "serverPlayer": "116846", "serverReceiver": "145799", "serverNext": "116846", "serverCompetitor": "116846", "receiverNext": "145799"}, "resultSet": null, "matchDateTime": {"duration": "00:21:15", "startDateLocal": "09/19/2024 19:30:00", "startDateUTC": "09/19/2024 17:30:00"}, "teamParentData": null, "playByPlaySequenceNumber": "148", "teamMatchNo": "0", "teamMatchScores": "0-0,0-0,0-0,0-0,0-0", "teamMatchScoresSummary": "0", "matchStartTimeUTC": null}