{"eventId": "2738", "documentCode": "TTEWSINGLES-----------R32-001300----------", "subEventName": "Women's Singles", "subEventDescription": "Women's Singles - Round of 32 - Match 13", "matchConfig": {"bestOfXGames": 5, "maxPointsPerGame": 11, "advantagePerGame": 2, "suddenDeathPoint": 99, "maxChallengesPerCompetitor": 99, "yellowCard": true, "yellowRed1": true, "yellowRed2": true, "tTRReview": false}, "venueName": "Erikdalshallen", "tableNumber": "T03", "tableName": "Table 3", "competitiors": [{"competitorType": "H", "competitiorId": "119542", "competitiorName": "MORI Sakura", "competitiorOrg": "JPN", "compCardY": "0", "compCardYR1": "0", "compCardYR2": "0", "compTimeout": "1", "compMedicalTimeout": "", "players": [{"playerId": "119542", "playerName": "MORI Sakura", "playerGivenName": null, "playerFamilyName": null, "playerOrgCode": "JPN", "playerPosition": 1}], "scores": "9,11,15,11,0", "irm": null}, {"competitorType": "A", "competitiorId": "133593", "competitiorName": "GHOSH Swastika", "competitiorOrg": "IND", "compCardY": "0", "compCardYR1": "0", "compCardYR2": "0", "compTimeout": "1", "compMedicalTimeout": "", "players": [{"playerId": "133593", "playerName": "GHOSH Swastika", "playerGivenName": null, "playerFamilyName": null, "playerOrgCode": "IND", "playerPosition": 2}], "scores": "11,3,13,5,0", "irm": null}], "currentGameNumber": 4, "full_msg": null, "gameScores": "9-11,11-3,15-13,11-5,0-0", "resultsGameScores": "9-11,11-3,15-13,11-5,0-0", "overallScores": "3-1", "resultOverallScores": "3-1", "resultStatus": "OFFICIAL", "action": {"actionType": "OF", "serverPlayer": "119542", "serverReceiver": "133593", "serverNext": "119542", "serverCompetitor": "119542", "receiverNext": "133593"}, "resultSet": null, "matchDateTime": {"duration": "00:34:30", "startDateLocal": "10/05/2023 13:30:00", "startDateUTC": "10/05/2023 11:30:00"}, "teamParentData": null, "playByPlaySequenceNumber": "221", "teamMatchNo": "0", "teamMatchScores": "0-0,0-0,0-0,0-0,0-0", "teamMatchScoresSummary": "0", "matchStartTimeUTC": null}