{"eventId": "3069", "documentCode": "TTEMSINGLES-----------R64-002300----------", "subEventName": "Men's Singles", "subEventDescription": "Men's Singles - Round of 64 - Match 23", "matchConfig": {"bestOfXGames": 5, "maxPointsPerGame": 11, "advantagePerGame": 2, "suddenDeathPoint": 99, "maxChallengesPerCompetitor": 99, "yellowCard": true, "yellowRed1": true, "yellowRed2": true, "tTRReview": false}, "venueName": "National Training Centre Havirov", "tableNumber": "T01", "tableName": "Table 1", "competitiors": [{"competitorType": "H", "competitiorId": "114410", "competitiorName": "RANEFUR Elias", "competitiorOrg": "SWE", "compCardY": "0", "compCardYR1": "0", "compCardYR2": "0", "compTimeout": "1", "compMedicalTimeout": "", "players": [{"playerId": "114410", "playerName": "RANEFUR Elias", "playerGivenName": null, "playerFamilyName": null, "playerOrgCode": "SWE", "playerPosition": 1}], "scores": "11,11,14,0,0", "irm": null}, {"competitorType": "A", "competitiorId": "123664", "competitiorName": "VALENTA Jan", "competitiorOrg": "CZE", "compCardY": "0", "compCardYR1": "0", "compCardYR2": "0", "compTimeout": "1", "compMedicalTimeout": "", "players": [{"playerId": "123664", "playerName": "VALENTA Jan", "playerGivenName": null, "playerFamilyName": null, "playerOrgCode": "CZE", "playerPosition": 2}], "scores": "6,9,12,0,0", "irm": null}], "currentGameNumber": 3, "full_msg": null, "gameScores": "11-6,11-9,14-12,0-0,0-0", "resultsGameScores": "11-6,11-9,14-12,0-0,0-0", "overallScores": "3-0", "resultOverallScores": "3-0", "resultStatus": "OFFICIAL", "action": {"actionType": "OF", "serverPlayer": "114410", "serverReceiver": "123664", "serverNext": "114410", "serverCompetitor": "114410", "receiverNext": "123664"}, "resultSet": null, "matchDateTime": {"duration": "00:26:23", "startDateLocal": "04/07/2025 14:05:00", "startDateUTC": "04/07/2025 12:05:00"}, "teamParentData": null, "playByPlaySequenceNumber": "187", "teamMatchNo": "0", "teamMatchScores": "0-0,0-0,0-0,0-0,0-0", "teamMatchScoresSummary": "0", "matchStartTimeUTC": "2025-04-07T12:18:12.657Z"}