{"eventId": "2592", "documentCode": "TTEMSINGLES-----------QFNL000400----------", "subEventName": "Men's Singles", "subEventDescription": "Men's Singles - Quarterfinal - Match 4", "matchConfig": {"bestOfXGames": 7, "maxPointsPerGame": 11, "advantagePerGame": 2, "suddenDeathPoint": 99, "maxChallengesPerCompetitor": 99, "yellowCard": true, "yellowRed1": true, "yellowRed2": true, "tTRReview": false}, "venueName": "BOK Hall", "tableNumber": "T01", "tableName": "Table 1", "competitiors": [{"competitorType": "H", "competitiorId": "133694", "competitiorName": "TOGAMI Shunsuke", "competitiorOrg": "JPN", "compCardY": "0", "compCardYR1": "0", "compCardYR2": "0", "compTimeout": "1", "compMedicalTimeout": "", "players": [{"playerId": "133694", "playerName": "TOGAMI Shunsuke", "playerGivenName": null, "playerFamilyName": null, "playerOrgCode": "JPN", "playerPosition": 1}], "scores": "2,9,10,7,0,0,0", "irm": null}, {"competitorType": "A", "competitiorId": "137237", "competitiorName": "LIN Shidong", "competitiorOrg": "CHN", "compCardY": "0", "compCardYR1": "0", "compCardYR2": "0", "compTimeout": "0", "compMedicalTimeout": "", "players": [{"playerId": "137237", "playerName": "LIN Shidong", "playerGivenName": null, "playerFamilyName": null, "playerOrgCode": "CHN", "playerPosition": 2}], "scores": "11,11,12,11,0,0,0", "irm": null}], "currentGameNumber": 4, "full_msg": null, "gameScores": "2-11,9-11,10-12,7-11,0-0,0-0,0-0", "resultsGameScores": "2-11,9-11,10-12,7-11,0-0,0-0,0-0", "overallScores": "0-4", "resultOverallScores": "0-4", "resultStatus": "OFFICIAL", "action": {"actionType": "OF", "serverPlayer": "", "serverReceiver": "", "serverNext": "", "serverCompetitor": "", "receiverNext": ""}, "resultSet": null, "matchDateTime": {"duration": "00:28:52", "startDateLocal": "07/21/2022 17:26:54", "startDateUTC": "07/21/2022 15:26:54"}, "teamParentData": null, "playByPlaySequenceNumber": "212", "teamMatchNo": "0", "teamMatchScores": "0-0,0-0,0-0,0-0,0-0", "teamMatchScoresSummary": "0", "matchStartTimeUTC": null}