{"eventId": "2660", "documentCode": "TTEMSINGLES-----------R64-001000----------", "subEventName": "Men's Singles", "subEventDescription": "Men's Singles - Round of 64 - Match 10", "matchConfig": {"bestOfXGames": 7, "maxPointsPerGame": 11, "advantagePerGame": 2, "suddenDeathPoint": 99, "maxChallengesPerCompetitor": 2, "yellowCard": true, "yellowRed1": true, "yellowRed2": true, "tTRReview": true}, "venueName": "ICC Durban", "tableNumber": "T03", "tableName": "Table 3", "competitiors": [{"competitorType": "H", "competitiorId": "102380", "competitiorName": "DRINKHALL Paul", "competitiorOrg": "ENG", "compCardY": "0", "compCardYR1": "0", "compCardYR2": "0", "compTimeout": "1", "compMedicalTimeout": "", "players": [{"playerId": "102380", "playerName": "DRINKHALL Paul", "playerGivenName": null, "playerFamilyName": null, "playerOrgCode": "ENG", "playerPosition": 1}], "scores": "12,9,11,9,15,11,0", "irm": null}, {"competitorType": "A", "competitiorId": "116680", "competitiorName": "ZELJKO Filip", "competitiorOrg": "CRO", "compCardY": "0", "compCardYR1": "0", "compCardYR2": "0", "compTimeout": "1", "compMedicalTimeout": "", "players": [{"playerId": "116680", "playerName": "ZELJKO Filip", "playerGivenName": null, "playerFamilyName": null, "playerOrgCode": "CRO", "playerPosition": 2}], "scores": "10,11,6,11,13,8,0", "irm": null}], "currentGameNumber": 6, "full_msg": null, "gameScores": "12-10,9-11,11-6,9-11,15-13,11-8,0-0", "resultsGameScores": "12-10,9-11,11-6,9-11,15-13,11-8,0-0", "overallScores": "4-2", "resultOverallScores": "4-2", "resultStatus": "OFFICIAL", "action": {"actionType": "OF", "serverPlayer": "116680", "serverReceiver": "102380", "serverNext": "116680", "serverCompetitor": "116680", "receiverNext": "102380"}, "resultSet": null, "matchDateTime": {"duration": "01:01:29", "startDateLocal": "05/22/2023 12:20:00", "startDateUTC": "05/22/2023 10:20:00"}, "teamParentData": null, "playByPlaySequenceNumber": "367", "teamMatchNo": "0", "teamMatchScores": "0-0,0-0,0-0,0-0,0-0", "teamMatchScoresSummary": "0", "matchStartTimeUTC": null}