{"eventId": "3082", "documentCode": "TTEWSINGLES-----------RND1002800----------", "subEventName": "Women's Singles", "subEventDescription": "Women's Singles Qualifying R 1 - Match 28", "matchConfig": {"bestOfXGames": 5, "maxPointsPerGame": 11, "advantagePerGame": 2, "suddenDeathPoint": 99, "maxChallengesPerCompetitor": 2, "yellowCard": true, "yellowRed1": true, "yellowRed2": true, "tTRReview": true}, "venueName": "Orleans Arena", "tableNumber": "T02", "tableName": "Table 2", "competitiors": [{"competitorType": "H", "competitiorId": "121041", "competitiorName": "WEGRZYN Katarzyna", "competitiorOrg": "POL", "compCardY": "1", "compCardYR1": "0", "compCardYR2": "0", "compTimeout": "1", "compMedicalTimeout": "", "players": [{"playerId": "121041", "playerName": "WEGRZYN Katarzyna", "playerGivenName": null, "playerFamilyName": null, "playerOrgCode": "POL", "playerPosition": 1}], "scores": "11,7,11,6,0", "irm": null}, {"competitorType": "A", "competitiorId": "105913", "competitiorName": "MATELOVA Hana", "competitiorOrg": "CZE", "compCardY": "0", "compCardYR1": "0", "compCardYR2": "0", "compTimeout": "0", "compMedicalTimeout": "", "players": [{"playerId": "105913", "playerName": "MATELOVA Hana", "playerGivenName": null, "playerFamilyName": null, "playerOrgCode": "CZE", "playerPosition": 2}], "scores": "6,11,13,11,0", "irm": null}], "currentGameNumber": 4, "full_msg": null, "gameScores": "11-6,7-11,11-13,6-11,0-0", "resultsGameScores": "11-6,7-11,11-13,6-11,0-0", "overallScores": "1-3", "resultOverallScores": "1-3", "resultStatus": "OFFICIAL", "action": {"actionType": "OF", "serverPlayer": "105913", "serverReceiver": "121041", "serverNext": "105913", "serverCompetitor": "105913", "receiverNext": "121041"}, "resultSet": null, "matchDateTime": {"duration": "00:25:57", "startDateLocal": "07/04/2025 12:00:00", "startDateUTC": "07/04/2025 19:00:00"}, "teamParentData": null, "playByPlaySequenceNumber": "215", "teamMatchNo": "0", "teamMatchScores": "0-0,0-0,0-0,0-0,0-0", "teamMatchScoresSummary": "0", "matchStartTimeUTC": null}