{"eventId": "2983", "documentCode": "TTEMSINGLES-----------R32-000200----------", "subEventName": "Men's Singles", "subEventDescription": "Men's Singles - Round of 32 - Match 2", "matchConfig": {"bestOfXGames": 5, "maxPointsPerGame": 11, "advantagePerGame": 2, "suddenDeathPoint": 99, "maxChallengesPerCompetitor": 99, "yellowCard": true, "yellowRed1": true, "yellowRed2": true, "tTRReview": false}, "venueName": "Macao East Asian Games Dome", "tableNumber": "T01", "tableName": "Table 1", "competitiors": [{"competitorType": "H", "competitiorId": "131148", "competitiorName": "XU Yingbin", "competitiorOrg": "CHN", "compCardY": "0", "compCardYR1": "0", "compCardYR2": "0", "compTimeout": "1", "compMedicalTimeout": "", "players": [{"playerId": "131148", "playerName": "XU Yingbin", "playerGivenName": null, "playerFamilyName": null, "playerOrgCode": "CHN", "playerPosition": 1}], "scores": "11,8,11,8,11", "irm": null}, {"competitorType": "A", "competitiorId": "101820", "competitiorName": "CHUANG Chih-Yuan", "competitiorOrg": "TPE", "compCardY": "0", "compCardYR1": "0", "compCardYR2": "0", "compTimeout": "1", "compMedicalTimeout": "", "players": [{"playerId": "101820", "playerName": "CHUANG Chih-Yuan", "playerGivenName": null, "playerFamilyName": null, "playerOrgCode": "TPE", "playerPosition": 2}], "scores": "8,11,4,11,7", "irm": null}], "currentGameNumber": 5, "full_msg": null, "gameScores": "11-8,8-11,11-4,8-11,11-7", "resultsGameScores": "11-8,8-11,11-4,8-11,11-7", "overallScores": "3-2", "resultOverallScores": "3-2", "resultStatus": "OFFICIAL", "action": {"actionType": "OF", "serverPlayer": "131148", "serverReceiver": "101820", "serverNext": "131148", "serverCompetitor": "131148", "receiverNext": "101820"}, "resultSet": null, "matchDateTime": {"duration": "00:40:04", "startDateLocal": "09/11/2024 14:15:00", "startDateUTC": "09/11/2024 06:15:00"}, "teamParentData": null, "playByPlaySequenceNumber": "263", "teamMatchNo": "0", "teamMatchScores": "0-0,0-0,0-0,0-0,0-0", "teamMatchScoresSummary": "0", "matchStartTimeUTC": null}