{"eventId": "2873", "documentCode": "TTEWSINGLES-----------RND3000200----------", "subEventName": "Women's Singles", "subEventDescription": "Women's Singles - Qualifying Round 3 - Match 2", "matchConfig": {"bestOfXGames": 5, "maxPointsPerGame": 11, "advantagePerGame": 2, "suddenDeathPoint": 99, "maxChallengesPerCompetitor": 99, "yellowCard": true, "yellowRed1": true, "yellowRed2": true, "tTRReview": false}, "venueName": "Table Tennis Centre ADD", "tableNumber": "T02", "tableName": "Table 2", "competitiors": [{"competitorType": "H", "competitiorId": "136309", "competitiorName": "AKAE Kaho", "competitiorOrg": "JPN", "compCardY": "0", "compCardYR1": "0", "compCardYR2": "0", "compTimeout": "0", "compMedicalTimeout": "", "players": [{"playerId": "136309", "playerName": "AKAE Kaho", "playerGivenName": null, "playerFamilyName": null, "playerOrgCode": "JPN", "playerPosition": 1}], "scores": "9,11,5,8,0", "irm": null}, {"competitorType": "A", "competitiorId": "132715", "competitiorName": "YOO Siwoo", "competitiorOrg": "KOR", "compCardY": "0", "compCardYR1": "0", "compCardYR2": "0", "compTimeout": "0", "compMedicalTimeout": "", "players": [{"playerId": "132715", "playerName": "YOO Siwoo", "playerGivenName": null, "playerFamilyName": null, "playerOrgCode": "KOR", "playerPosition": 2}], "scores": "11,5,11,11,0", "irm": null}], "currentGameNumber": 4, "full_msg": null, "gameScores": "9-11,11-5,5-11,8-11,0-0", "resultsGameScores": "9-11,11-5,5-11,8-11,0-0", "overallScores": "1-3", "resultOverallScores": "1-3", "resultStatus": "OFFICIAL", "action": {"actionType": "OF", "serverPlayer": "136309", "serverReceiver": "132715", "serverNext": "136309", "serverCompetitor": "136309", "receiverNext": "132715"}, "resultSet": null, "matchDateTime": {"duration": "00:30:20", "startDateLocal": "09/04/2024 12:55:00", "startDateUTC": "09/04/2024 07:55:00"}, "teamParentData": null, "playByPlaySequenceNumber": "197", "teamMatchNo": "0", "teamMatchScores": "0-0,0-0,0-0,0-0,0-0", "teamMatchScoresSummary": "0", "matchStartTimeUTC": null}