{"eventId": "3092", "documentCode": "TTEWSINGLES-----------R32-000700----------", "subEventName": "Women's Singles", "subEventDescription": "Women's Singles - Round of 32 - Match 7", "matchConfig": {"bestOfXGames": 5, "maxPointsPerGame": 11, "advantagePerGame": 2, "suddenDeathPoint": 99, "maxChallengesPerCompetitor": 99, "yellowCard": true, "yellowRed1": true, "yellowRed2": true, "tTRReview": false}, "venueName": "Arena Zagreb", "tableNumber": "T02", "tableName": "Table 2", "competitiors": [{"competitorType": "H", "competitiorId": "137627", "competitiorName": "LIU Yangzi", "competitiorOrg": "AUS", "compCardY": "0", "compCardYR1": "0", "compCardYR2": "0", "compTimeout": "1", "compMedicalTimeout": "", "players": [{"playerId": "137627", "playerName": "LIU Yangzi", "playerGivenName": null, "playerFamilyName": null, "playerOrgCode": "AUS", "playerPosition": 1}], "scores": "11,5,8,5,0", "irm": null}, {"competitorType": "A", "competitiorId": "133901", "competitiorName": "ZHANG Xiangyu", "competitiorOrg": "CHN", "compCardY": "0", "compCardYR1": "0", "compCardYR2": "0", "compTimeout": "1", "compMedicalTimeout": "", "players": [{"playerId": "133901", "playerName": "ZHANG Xiangyu", "playerGivenName": null, "playerFamilyName": null, "playerOrgCode": "CHN", "playerPosition": 2}], "scores": "7,11,11,11,0", "irm": null}], "currentGameNumber": 4, "full_msg": null, "gameScores": "11-7,5-11,8-11,5-11,0-0", "resultsGameScores": "11-7,5-11,8-11,5-11,0-0", "overallScores": "1-3", "resultOverallScores": "1-3", "resultStatus": "OFFICIAL", "action": {"actionType": "OF", "serverPlayer": "137627", "serverReceiver": "133901", "serverNext": "137627", "serverCompetitor": "137627", "receiverNext": "133901"}, "resultSet": null, "matchDateTime": {"duration": "00:28:49", "startDateLocal": "06/26/2025 20:25:00", "startDateUTC": "06/26/2025 18:25:00"}, "teamParentData": null, "playByPlaySequenceNumber": "199", "teamMatchNo": "0", "teamMatchScores": "0-0,0-0,0-0,0-0,0-0", "teamMatchScoresSummary": "0", "matchStartTimeUTC": null}