{"eventId": "2695", "documentCode": "TTEWSINGLES-----------SFNL000100----------", "subEventName": "Women's Singles", "subEventDescription": "Women's Singles - Semifinal - Match 1", "matchConfig": {"bestOfXGames": 5, "maxPointsPerGame": 11, "advantagePerGame": 2, "suddenDeathPoint": 99, "maxChallengesPerCompetitor": 99, "yellowCard": true, "yellowRed1": true, "yellowRed2": true, "tTRReview": false}, "venueName": "Huamark Indoor Stadium", "tableNumber": "T01", "tableName": "Table 1", "competitiors": [{"competitorType": "H", "competitiorId": "121403", "competitiorName": "CHEN Xingtong", "competitiorOrg": "CHN", "compCardY": "0", "compCardYR1": "0", "compCardYR2": "0", "compTimeout": "1", "compMedicalTimeout": "", "players": [{"playerId": "121403", "playerName": "CHEN Xingtong", "playerGivenName": null, "playerFamilyName": null, "playerOrgCode": "CHN", "playerPosition": 1}], "scores": "11,8,11,5,11", "irm": null}, {"competitorType": "A", "competitiorId": "115009", "competitiorName": "DIAZ Adriana", "competitiorOrg": "PUR", "compCardY": "0", "compCardYR1": "0", "compCardYR2": "0", "compTimeout": "1", "compMedicalTimeout": "", "players": [{"playerId": "115009", "playerName": "DIAZ Adriana", "playerGivenName": null, "playerFamilyName": null, "playerOrgCode": "PUR", "playerPosition": 2}], "scores": "6,11,5,11,4", "irm": null}], "currentGameNumber": 5, "full_msg": null, "gameScores": "11-6,8-11,11-5,5-11,11-4", "resultsGameScores": "11-6,8-11,11-5,5-11,11-4", "overallScores": "3-2", "resultOverallScores": "3-2", "resultStatus": "OFFICIAL", "action": {"actionType": "OF", "serverPlayer": "115009", "serverReceiver": "121403", "serverNext": "115009", "serverCompetitor": "115009", "receiverNext": "121403"}, "resultSet": null, "matchDateTime": {"duration": "00:39:31", "startDateLocal": "04/28/2023 21:00:00", "startDateUTC": "04/28/2023 14:00:00"}, "teamParentData": null, "playByPlaySequenceNumber": "227", "teamMatchNo": "0", "teamMatchScores": "0-0,0-0,0-0,0-0,0-0", "teamMatchScoresSummary": "0", "matchStartTimeUTC": null}