{"eventId": "2940", "documentCode": "TTEWSINGLES-----------R32-000300----------", "subEventName": "Women's Singles", "subEventDescription": "Women's Singles - Round of 32 - Match 3", "matchConfig": {"bestOfXGames": 5, "maxPointsPerGame": 11, "advantagePerGame": 2, "suddenDeathPoint": 99, "maxChallengesPerCompetitor": 99, "yellowCard": true, "yellowRed1": true, "yellowRed2": true, "tTRReview": false}, "venueName": "Sud de France ARENA", "tableNumber": "T01", "tableName": "Table 1", "competitiors": [{"competitorType": "H", "competitiorId": "112221", "competitiorName": "ZHANG Lily", "competitiorOrg": "USA", "compCardY": "0", "compCardYR1": "0", "compCardYR2": "0", "compTimeout": "0", "compMedicalTimeout": "", "players": [{"playerId": "112221", "playerName": "ZHANG Lily", "playerGivenName": null, "playerFamilyName": null, "playerOrgCode": "USA", "playerPosition": 1}], "scores": "4,8,10,0,0", "irm": null}, {"competitorType": "A", "competitiorId": "115920", "competitiorName": "BATRA Manika", "competitiorOrg": "IND", "compCardY": "0", "compCardYR1": "0", "compCardYR2": "0", "compTimeout": "0", "compMedicalTimeout": "", "players": [{"playerId": "115920", "playerName": "BATRA Manika", "playerGivenName": null, "playerFamilyName": null, "playerOrgCode": "IND", "playerPosition": 2}], "scores": "11,11,12,0,0", "irm": null}], "currentGameNumber": 3, "full_msg": null, "gameScores": "4-11,8-11,10-12,0-0,0-0", "resultsGameScores": "4-11,8-11,10-12,0-0,0-0", "overallScores": "0-3", "resultOverallScores": "0-3", "resultStatus": "OFFICIAL", "action": {"actionType": "OF", "serverPlayer": "115920", "serverReceiver": "112221", "serverNext": "115920", "serverCompetitor": "115920", "receiverNext": "112221"}, "resultSet": null, "matchDateTime": {"duration": "00:21:54", "startDateLocal": "10/23/2024 15:20:00", "startDateUTC": "10/23/2024 12:20:00"}, "teamParentData": null, "playByPlaySequenceNumber": "153", "teamMatchNo": "0", "teamMatchScores": "0-0,0-0,0-0,0-0,0-0", "teamMatchScoresSummary": "0", "matchStartTimeUTC": null}