{"eventId": "2734", "documentCode": "TTEMSINGLES-----------R64-002600----------", "subEventName": "Men's Singles", "subEventDescription": "Men's Singles - Round of 64 - Match 26", "matchConfig": {"bestOfXGames": 5, "maxPointsPerGame": 11, "advantagePerGame": 2, "suddenDeathPoint": 99, "maxChallengesPerCompetitor": 99, "yellowCard": true, "yellowRed1": true, "yellowRed2": true, "tTRReview": false}, "venueName": "Aspire Ladies Sports Hall", "tableNumber": "T05", "tableName": "Table 5", "competitiors": [{"competitorType": "H", "competitiorId": "144666", "competitiorName": "ABDALLA Yousif", "competitiorOrg": "QAT", "compCardY": "0", "compCardYR1": "0", "compCardYR2": "0", "compTimeout": "0", "compMedicalTimeout": "", "players": [{"playerId": "144666", "playerName": "ABDALLA Yousif", "playerGivenName": null, "playerFamilyName": null, "playerOrgCode": "QAT", "playerPosition": 1}], "scores": "11,10,11,3,11", "irm": null}, {"competitorType": "A", "competitiorId": "144667", "competitiorName": "ABDULWAHHAB Abdullah", "competitiorOrg": "QAT", "compCardY": "0", "compCardYR1": "0", "compCardYR2": "0", "compTimeout": "1", "compMedicalTimeout": "", "players": [{"playerId": "144667", "playerName": "ABDULWAHHAB Abdullah", "playerGivenName": null, "playerFamilyName": null, "playerOrgCode": "QAT", "playerPosition": 2}], "scores": "8,12,5,11,9", "irm": null}], "currentGameNumber": 5, "full_msg": null, "gameScores": "11-8,10-12,11-5,3-11,11-9", "resultsGameScores": "11-8,10-12,11-5,3-11,11-9", "overallScores": "3-2", "resultOverallScores": "3-2", "resultStatus": "OFFICIAL", "action": {"actionType": "OF", "serverPlayer": "144666", "serverReceiver": "144667", "serverNext": "144666", "serverCompetitor": "144666", "receiverNext": "144667"}, "resultSet": null, "matchDateTime": {"duration": "00:26:59", "startDateLocal": "10/17/2023 12:20:00", "startDateUTC": "10/17/2023 10:20:00"}, "teamParentData": null, "playByPlaySequenceNumber": "247", "teamMatchNo": "0", "teamMatchScores": "0-0,0-0,0-0,0-0,0-0", "teamMatchScoresSummary": "0", "matchStartTimeUTC": null}