{"eventId": "2733", "documentCode": "TTEMSINGLES-----------RND2000200----------", "subEventName": "Men's Singles", "subEventDescription": "Men's Singles - Qualifying Round 2 - Match 2", "matchConfig": {"bestOfXGames": 5, "maxPointsPerGame": 11, "advantagePerGame": 2, "suddenDeathPoint": 99, "maxChallengesPerCompetitor": 99, "yellowCard": true, "yellowRed1": true, "yellowRed2": true, "tTRReview": false}, "venueName": "Sport Centre Otocec", "tableNumber": "T02", "tableName": "Table 2", "competitiors": [{"competitorType": "H", "competitiorId": "133274", "competitiorName": "KOGANS Daniels", "competitiorOrg": "LAT", "compCardY": "0", "compCardYR1": "0", "compCardYR2": "0", "compTimeout": "1", "compMedicalTimeout": "", "players": [{"playerId": "133274", "playerName": "KOGANS Daniels", "playerGivenName": null, "playerFamilyName": null, "playerOrgCode": "LAT", "playerPosition": 1}], "scores": "9,14,7,0,0", "irm": null}, {"competitorType": "A", "competitiorId": "134398", "competitiorName": "KHARKI Iskender", "competitiorOrg": "KAZ", "compCardY": "0", "compCardYR1": "0", "compCardYR2": "0", "compTimeout": "1", "compMedicalTimeout": "", "players": [{"playerId": "134398", "playerName": "KHARKI Iskender", "playerGivenName": null, "playerFamilyName": null, "playerOrgCode": "KAZ", "playerPosition": 2}], "scores": "11,16,11,0,0", "irm": null}], "currentGameNumber": 3, "full_msg": null, "gameScores": "9-11,14-16,7-11,0-0,0-0", "resultsGameScores": "9-11,14-16,7-11,0-0,0-0", "overallScores": "0-3", "resultOverallScores": "0-3", "resultStatus": "OFFICIAL", "action": {"actionType": "OF", "serverPlayer": "134398", "serverReceiver": "133274", "serverNext": "134398", "serverCompetitor": "134398", "receiverNext": "133274"}, "resultSet": null, "matchDateTime": {"duration": "00:28:04", "startDateLocal": "10/31/2023 12:20:00", "startDateUTC": "10/31/2023 11:20:00"}, "teamParentData": null, "playByPlaySequenceNumber": "195", "teamMatchNo": "0", "teamMatchScores": "0-0,0-0,0-0,0-0,0-0", "teamMatchScoresSummary": "0", "matchStartTimeUTC": null}