{"eventId": "2658", "documentCode": "TTEWSINGLES-----------RND1000300----------", "subEventName": "Women's Singles", "subEventDescription": "Women's Singles - Preliminary Round 1 - Match 3", "matchConfig": {"bestOfXGames": 5, "maxPointsPerGame": 11, "advantagePerGame": 2, "suddenDeathPoint": 99, "maxChallengesPerCompetitor": 99, "yellowCard": true, "yellowRed1": true, "yellowRed2": true, "tTRReview": false}, "venueName": "Deutsches Tischtennis- Zentrum", "tableNumber": "T02", "tableName": "Table 2", "competitiors": [{"competitorType": "H", "competitiorId": "133026", "competitiorName": "YILMAZ Ozge", "competitiorOrg": "TUR", "compCardY": "0", "compCardYR1": "0", "compCardYR2": "0", "compTimeout": "1", "compMedicalTimeout": "", "players": [{"playerId": "133026", "playerName": "YILMAZ Ozge", "playerGivenName": null, "playerFamilyName": null, "playerOrgCode": "TUR", "playerPosition": 1}], "scores": "11,11,10,7,13", "irm": null}, {"competitorType": "A", "competitiorId": "201271", "competitiorName": "MAK Ming Shum", "competitiorOrg": "HKG", "compCardY": "0", "compCardYR1": "0", "compCardYR2": "0", "compTimeout": "1", "compMedicalTimeout": "", "players": [{"playerId": "201271", "playerName": "MAK Ming Shum", "playerGivenName": null, "playerFamilyName": null, "playerOrgCode": "HKG", "playerPosition": 2}], "scores": "9,3,12,11,11", "irm": null}], "currentGameNumber": 5, "full_msg": null, "gameScores": "11-9,11-3,10-12,7-11,13-11", "resultsGameScores": "11-9,11-3,10-12,7-11,13-11", "overallScores": "3-2", "resultOverallScores": "3-2", "resultStatus": "OFFICIAL", "action": {"actionType": "OF", "serverPlayer": "133026", "serverReceiver": "201271", "serverNext": "133026", "serverCompetitor": "133026", "receiverNext": "201271"}, "resultSet": null, "matchDateTime": {"duration": "00:37:27", "startDateLocal": "11/22/2022 09:00:00", "startDateUTC": "11/22/2022 08:00:00"}, "teamParentData": null, "playByPlaySequenceNumber": "272", "teamMatchNo": "0", "teamMatchScores": "0-0,0-0,0-0,0-0,0-0", "teamMatchScoresSummary": "0", "matchStartTimeUTC": null}