{"eventId": "2867", "documentCode": "TTEMSINGLES-----------RND3000300----------", "subEventName": "Men's Singles", "subEventDescription": "Men's Singles - Qualifying Round 3 - Match 3", "matchConfig": {"bestOfXGames": 5, "maxPointsPerGame": 11, "advantagePerGame": 2, "suddenDeathPoint": 99, "maxChallengesPerCompetitor": 99, "yellowCard": true, "yellowRed1": true, "yellowRed2": true, "tTRReview": false}, "venueName": "Arena Carioca 1", "tableNumber": "T03", "tableName": "Table 3", "competitiors": [{"competitorType": "H", "competitiorId": "116612", "competitiorName": "AKKUZU Can", "competitiorOrg": "FRA", "compCardY": "0", "compCardYR1": "0", "compCardYR2": "0", "compTimeout": "1", "compMedicalTimeout": "", "players": [{"playerId": "116612", "playerName": "AKKUZU Can", "playerGivenName": null, "playerFamilyName": null, "playerOrgCode": "FRA", "playerPosition": 1}], "scores": "7,11,10,11,11", "irm": null}, {"competitorType": "A", "competitiorId": "131917", "competitiorName": "JAIN Payas", "competitiorOrg": "IND", "compCardY": "0", "compCardYR1": "0", "compCardYR2": "0", "compTimeout": "1", "compMedicalTimeout": "", "players": [{"playerId": "131917", "playerName": "JAIN Payas", "playerGivenName": null, "playerFamilyName": null, "playerOrgCode": "IND", "playerPosition": 2}], "scores": "11,4,12,7,4", "irm": null}], "currentGameNumber": 5, "full_msg": null, "gameScores": "7-11,11-4,10-12,11-7,11-4", "resultsGameScores": "7-11,11-4,10-12,11-7,11-4", "overallScores": "3-2", "resultOverallScores": "3-2", "resultStatus": "OFFICIAL", "action": {"actionType": "OF", "serverPlayer": "116612", "serverReceiver": "131917", "serverNext": "116612", "serverCompetitor": "116612", "receiverNext": "131917"}, "resultSet": null, "matchDateTime": {"duration": "00:43:05", "startDateLocal": "05/22/2024 15:45:00", "startDateUTC": "05/22/2024 18:45:00"}, "teamParentData": null, "playByPlaySequenceNumber": "254", "teamMatchNo": "0", "teamMatchScores": "0-0,0-0,0-0,0-0,0-0", "teamMatchScoresSummary": "0", "matchStartTimeUTC": null}