{"eventId": "2755", "documentCode": "TTEMSINGLES-----------RND3001500----------", "subEventName": "Men's Singles", "subEventDescription": "Men's Singles - Qualifying Round 3 - Match 15", "matchConfig": {"bestOfXGames": 5, "maxPointsPerGame": 11, "advantagePerGame": 2, "suddenDeathPoint": 99, "maxChallengesPerCompetitor": 99, "yellowCard": true, "yellowRed1": true, "yellowRed2": true, "tTRReview": false}, "venueName": "Deutsches Tischtennis- Zentrum", "tableNumber": "T02", "tableName": "Table 2", "competitiors": [{"competitorType": "H", "competitiorId": "131211", "competitiorName": "HAUG Borgar", "competitiorOrg": "NOR", "compCardY": "0", "compCardYR1": "0", "compCardYR2": "0", "compTimeout": "0", "compMedicalTimeout": "", "players": [{"playerId": "131211", "playerName": "HAUG Borgar", "playerGivenName": null, "playerFamilyName": null, "playerOrgCode": "NOR", "playerPosition": 1}], "scores": "11,8,11,11,0", "irm": null}, {"competitorType": "A", "competitiorId": "121940", "competitiorName": "SHAMS Navid", "competitiorOrg": "IRI", "compCardY": "0", "compCardYR1": "0", "compCardYR2": "0", "compTimeout": "1", "compMedicalTimeout": "", "players": [{"playerId": "121940", "playerName": "SHAMS Navid", "playerGivenName": null, "playerFamilyName": null, "playerOrgCode": "IRI", "playerPosition": 2}], "scores": "9,11,4,6,0", "irm": null}], "currentGameNumber": 4, "full_msg": null, "gameScores": "11-9,8-11,11-4,11-6,0-0", "resultsGameScores": "11-9,8-11,11-4,11-6,0-0", "overallScores": "3-1", "resultOverallScores": "3-1", "resultStatus": "OFFICIAL", "action": {"actionType": "OF", "serverPlayer": "131211", "serverReceiver": "121940", "serverNext": "131211", "serverCompetitor": "131211", "receiverNext": "121940"}, "resultSet": null, "matchDateTime": {"duration": "00:29:12", "startDateLocal": "11/28/2023 11:45:00", "startDateUTC": "11/28/2023 10:45:00"}, "teamParentData": null, "playByPlaySequenceNumber": "196", "teamMatchNo": "0", "teamMatchScores": "0-0,0-0,0-0,0-0,0-0", "teamMatchScoresSummary": "0", "matchStartTimeUTC": null}