{"eventId": "2540", "documentCode": "TTEMSINGLES-----------RND1000600----------", "subEventName": "Men's Singles", "subEventDescription": "Men's Singles - Qualifying Round 1 - Match 6", "matchConfig": {"bestOfXGames": 5, "maxPointsPerGame": 11, "advantagePerGame": 2, "suddenDeathPoint": 99, "maxChallengesPerCompetitor": 99, "yellowCard": true, "yellowRed1": true, "yellowRed2": true, "tTRReview": false}, "venueName": "Sport Centre Otocec", "tableNumber": "T04", "tableName": "Table 4", "competitiors": [{"competitorType": "H", "competitiorId": "107762", "competitiorName": "RECH DALDOSSO Marco", "competitiorOrg": "ITA", "compCardY": "0", "compCardYR1": "0", "compCardYR2": "0", "compTimeout": "1", "compMedicalTimeout": "", "players": [{"playerId": "107762", "playerName": "RECH DALDOSSO Marco", "playerGivenName": null, "playerFamilyName": null, "playerOrgCode": "ITA", "playerPosition": 1}], "scores": "11,7,11,5,6", "irm": null}, {"competitorType": "A", "competitiorId": "133341", "competitiorName": "HARDMEIER Elias", "competitiorOrg": "SUI", "compCardY": "0", "compCardYR1": "0", "compCardYR2": "0", "compTimeout": "0", "compMedicalTimeout": "", "players": [{"playerId": "133341", "playerName": "HARDMEIER Elias", "playerGivenName": null, "playerFamilyName": null, "playerOrgCode": "SUI", "playerPosition": 2}], "scores": "6,11,9,11,11", "irm": null}], "currentGameNumber": 5, "full_msg": null, "gameScores": "11-6,7-11,11-9,5-11,6-11", "resultsGameScores": "11-6,7-11,11-9,5-11,6-11", "overallScores": "2-3", "resultOverallScores": "2-3", "resultStatus": "OFFICIAL", "action": {"actionType": "OF", "serverPlayer": "", "serverReceiver": "", "serverNext": "", "serverCompetitor": "", "receiverNext": ""}, "resultSet": null, "matchDateTime": {"duration": "00:40:42", "startDateLocal": "06/21/2022 10:01:23", "startDateUTC": "06/21/2022 08:01:23"}, "teamParentData": null, "playByPlaySequenceNumber": "246", "teamMatchNo": "0", "teamMatchScores": "0-0,0-0,0-0,0-0,0-0", "teamMatchScoresSummary": "0", "matchStartTimeUTC": null}