{"eventId": "2735", "documentCode": "TTEMSINGLES-----------RND3000200----------", "subEventName": "Men's Singles", "subEventDescription": "Men's Singles - Qualifying Round 3 - Match 2", "matchConfig": {"bestOfXGames": 5, "maxPointsPerGame": 11, "advantagePerGame": 2, "suddenDeathPoint": 99, "maxChallengesPerCompetitor": 99, "yellowCard": true, "yellowRed1": true, "yellowRed2": true, "tTRReview": false}, "venueName": "Pavilhao Desportivo Municipal de Vila Nova de Gaia", "tableNumber": "T02", "tableName": "Table 2", "competitiors": [{"competitorType": "H", "competitiorId": "113329", "competitiorName": "LAKATOS Tamas", "competitiorOrg": "HUN", "compCardY": "0", "compCardYR1": "0", "compCardYR2": "0", "compTimeout": "0", "compMedicalTimeout": "", "players": [{"playerId": "113329", "playerName": "LAKATOS Tamas", "playerGivenName": null, "playerFamilyName": null, "playerOrgCode": "HUN", "playerPosition": 1}], "scores": "7,13,13,11,0", "irm": null}, {"competitorType": "A", "competitiorId": "117006", "competitiorName": "PICCOLIN Jordy", "competitiorOrg": "ITA", "compCardY": "0", "compCardYR1": "0", "compCardYR2": "0", "compTimeout": "1", "compMedicalTimeout": "", "players": [{"playerId": "117006", "playerName": "PICCOLIN Jordy", "playerGivenName": null, "playerFamilyName": null, "playerOrgCode": "ITA", "playerPosition": 2}], "scores": "11,11,11,5,0", "irm": null}], "currentGameNumber": 4, "full_msg": null, "gameScores": "7-11,13-11,13-11,11-5,0-0", "resultsGameScores": "7-11,13-11,13-11,11-5,0-0", "overallScores": "3-1", "resultOverallScores": "3-1", "resultStatus": "OFFICIAL", "action": {"actionType": "OF", "serverPlayer": "117006", "serverReceiver": "113329", "serverNext": "117006", "serverCompetitor": "117006", "receiverNext": "113329"}, "resultSet": null, "matchDateTime": {"duration": "00:37:39", "startDateLocal": "11/22/2023 20:05:00", "startDateUTC": "11/22/2023 20:05:00"}, "teamParentData": null, "playByPlaySequenceNumber": "238", "teamMatchNo": "0", "teamMatchScores": "0-0,0-0,0-0,0-0,0-0", "teamMatchScoresSummary": "0", "matchStartTimeUTC": null}