{"eventId": "2870", "documentCode": "TTEWSINGLES-----------RND1002100----------", "subEventName": "Women's Singles", "subEventDescription": "Women's Singles - Qualifying Round 1 - Match 21", "matchConfig": {"bestOfXGames": 5, "maxPointsPerGame": 11, "advantagePerGame": 2, "suddenDeathPoint": 99, "maxChallengesPerCompetitor": 99, "yellowCard": true, "yellowRed1": true, "yellowRed2": true, "tTRReview": false}, "venueName": "Hala Tivoli", "tableNumber": "T03", "tableName": "Table 3", "competitiors": [{"competitorType": "H", "competitiorId": "113908", "competitiorName": "HELMY Yousra", "competitiorOrg": "EGY", "compCardY": "0", "compCardYR1": "0", "compCardYR2": "0", "compTimeout": "1", "compMedicalTimeout": "", "players": [{"playerId": "113908", "playerName": "HELMY Yousra", "playerGivenName": null, "playerFamilyName": null, "playerOrgCode": "EGY", "playerPosition": 1}], "scores": "4,11,11,8,11", "irm": null}, {"competitorType": "A", "competitiorId": "109453", "competitiorName": "TODOROVIC Andrea", "competitiorOrg": "SRB", "compCardY": "0", "compCardYR1": "0", "compCardYR2": "0", "compTimeout": "1", "compMedicalTimeout": "", "players": [{"playerId": "109453", "playerName": "TODOROVIC Andrea", "playerGivenName": null, "playerFamilyName": null, "playerOrgCode": "SRB", "playerPosition": 2}], "scores": "11,9,9,11,7", "irm": null}], "currentGameNumber": 5, "full_msg": null, "gameScores": "4-11,11-9,11-9,8-11,11-7", "resultsGameScores": "4-11,11-9,11-9,8-11,11-7", "overallScores": "3-2", "resultOverallScores": "3-2", "resultStatus": "OFFICIAL", "action": {"actionType": "OF", "serverPlayer": "109453", "serverReceiver": "113908", "serverNext": "109453", "serverCompetitor": "109453", "receiverNext": "113908"}, "resultSet": null, "matchDateTime": {"duration": "00:42:49", "startDateLocal": "06/11/2024 11:30:00", "startDateUTC": "06/11/2024 09:30:00"}, "teamParentData": null, "playByPlaySequenceNumber": "257", "teamMatchNo": "0", "teamMatchScores": "0-0,0-0,0-0,0-0,0-0", "teamMatchScoresSummary": "0", "matchStartTimeUTC": null}