{"eventId": "3108", "documentCode": "TTEWSINGLES-----------R64-000400----------", "subEventName": "Women's Singles", "subEventDescription": "Women's Singles - Round of 64 - Match 4", "matchConfig": {"bestOfXGames": 7, "maxPointsPerGame": 11, "advantagePerGame": 2, "suddenDeathPoint": 99, "maxChallengesPerCompetitor": 2, "yellowCard": true, "yellowRed1": true, "yellowRed2": true, "tTRReview": true}, "venueName": "Qatar University", "tableNumber": "T04", "tableName": "Table 4", "competitiors": [{"competitorType": "H", "competitiorId": "134369", "competitiorName": "SINGEORZAN Ioana", "competitiorOrg": "ROU", "compCardY": "0", "compCardYR1": "0", "compCardYR2": "0", "compTimeout": "1", "compMedicalTimeout": "", "players": [{"playerId": "134369", "playerName": "SINGEORZAN Ioana", "playerGivenName": null, "playerFamilyName": null, "playerOrgCode": "ROU", "playerPosition": 1}], "scores": "11,6,5,12,5,1,0", "irm": null}, {"competitorType": "A", "competitiorId": "123977", "competitiorName": "SHIN Yubin", "competitiorOrg": "KOR", "compCardY": "0", "compCardYR1": "0", "compCardYR2": "0", "compTimeout": "0", "compMedicalTimeout": "", "players": [{"playerId": "123977", "playerName": "SHIN Yubin", "playerGivenName": null, "playerFamilyName": null, "playerOrgCode": "KOR", "playerPosition": 2}], "scores": "9,11,11,10,11,11,0", "irm": null}], "currentGameNumber": 6, "full_msg": null, "gameScores": "11-9,6-11,5-11,12-10,5-11,1-11,0-0", "resultsGameScores": "11-9,6-11,5-11,12-10,5-11,1-11,0-0", "overallScores": "2-4", "resultOverallScores": "2-4", "resultStatus": "OFFICIAL", "action": {"actionType": "OF", "serverPlayer": "123977", "serverReceiver": "134369", "serverNext": "123977", "serverCompetitor": "123977", "receiverNext": "134369"}, "resultSet": null, "matchDateTime": {"duration": "00:43:55", "startDateLocal": "05/19/2025 16:40:00", "startDateUTC": "05/19/2025 13:40:00"}, "teamParentData": null, "playByPlaySequenceNumber": "280", "teamMatchNo": "0", "teamMatchScores": "0-0,0-0,0-0,0-0,0-0", "teamMatchScoresSummary": "0", "matchStartTimeUTC": null}