{"eventId": "2410", "documentCode": "TTEMSINGLES-----------RND1003400--", "subEventName": "Men Singles", "subEventDescription": "Men's Singles - Preliminary Round 1 - Match 34", "matchConfig": {"bestOfXGames": 5, "maxPointsPerGame": 11, "advantagePerGame": 2, "suddenDeathPoint": 99, "maxChallengesPerCompetitor": 2, "yellowCard": true, "yellowRed1": true, "yellowRed2": true, "tTRReview": null}, "venueName": "Lusail Sports Arena", "tableNumber": "T07", "tableName": "Table 7", "competitiors": [{"competitorType": "H", "competitiorId": "116680", "competitiorName": "Filip ZELJKO", "competitiorOrg": "CRO", "compCardY": null, "compCardYR1": null, "compCardYR2": null, "compTimeout": null, "compMedicalTimeout": null, "players": [{"playerId": "116680", "playerName": "Filip ZELJKO", "playerGivenName": "Filip", "playerFamilyName": "ZELJKO", "playerOrgCode": "CRO", "playerPosition": null}], "scores": null, "irm": null}, {"competitorType": "A", "competitiorId": "114973", "competitiorName": "Aliaksandr KHANIN", "competitiorOrg": "BLR", "compCardY": null, "compCardYR1": null, "compCardYR2": null, "compTimeout": null, "compMedicalTimeout": null, "players": [{"playerId": "114973", "playerName": "Aliaksandr KHANIN", "playerGivenName": "Aliaksandr", "playerFamilyName": "KHANIN", "playerOrgCode": "BLR", "playerPosition": null}], "scores": null, "irm": null}], "currentGameNumber": null, "full_msg": null, "gameScores": null, "resultsGameScores": "6-11,4-11,5-11", "overallScores": "0-3", "resultOverallScores": "0-3", "resultStatus": "OFFICIAL", "action": null, "resultSet": null, "matchDateTime": {"duration": "01:26:20", "startDateLocal": "02/28/2021 08:20:00", "startDateUTC": "02/28/2021 08:20:00"}, "teamParentData": null, "playByPlaySequenceNumber": null, "teamMatchNo": null, "teamMatchScores": null, "teamMatchScoresSummary": null, "matchStartTimeUTC": null}