{"eventId": "2521", "documentCode": "TTEWSINGLES-----------SFNL000100----------", "subEventName": "Women's Singles", "subEventDescription": "Women's Singles - Semifinals - Match 1", "matchConfig": {"bestOfXGames": 7, "maxPointsPerGame": 11, "advantagePerGame": 2, "suddenDeathPoint": 99, "maxChallengesPerCompetitor": 99, "yellowCard": true, "yellowRed1": true, "yellowRed2": true, "tTRReview": false}, "venueName": "Deutsches Tischtennis- Zentrum", "tableNumber": "T01", "tableName": "Table 1", "competitiors": [{"competitorType": "H", "competitiorId": "111849", "competitiorName": "SHAN Xiaona", "competitiorOrg": "GER", "compCardY": "0", "compCardYR1": "0", "compCardYR2": "0", "compTimeout": "1", "compMedicalTimeout": "", "players": [{"playerId": "111849", "playerName": "SHAN Xiaona", "playerGivenName": null, "playerFamilyName": null, "playerOrgCode": "GER", "playerPosition": 1}], "scores": "8,7,11,11,11,11,0", "irm": null}, {"competitorType": "A", "competitiorId": "111066", "competitiorName": "WINTER Sabine", "competitiorOrg": "GER", "compCardY": "0", "compCardYR1": "0", "compCardYR2": "0", "compTimeout": "1", "compMedicalTimeout": "", "players": [{"playerId": "111066", "playerName": "WINTER Sabine", "playerGivenName": null, "playerFamilyName": null, "playerOrgCode": "GER", "playerPosition": 2}], "scores": "11,11,4,4,9,6,0", "irm": null}], "currentGameNumber": 6, "full_msg": null, "gameScores": "8-11,7-11,11-4,11-4,11-9,11-6,0-0", "resultsGameScores": "8-11,7-11,11-4,11-4,11-9,11-6,0-0", "overallScores": "4-2", "resultOverallScores": "4-2", "resultStatus": "OFFICIAL", "action": {"actionType": "OF", "serverPlayer": "", "serverReceiver": "", "serverNext": "", "serverCompetitor": "", "receiverNext": ""}, "resultSet": null, "matchDateTime": {"duration": "00:48:14", "startDateLocal": "01/15/2022 10:04:45", "startDateUTC": "01/15/2022 09:04:45"}, "teamParentData": null, "playByPlaySequenceNumber": "288", "teamMatchNo": "0", "teamMatchScores": "0-0,0-0,0-0,0-0,0-0", "teamMatchScoresSummary": "0", "matchStartTimeUTC": null}